num2textilka.py
packages/__init__.py
packages/convertor.py
packages/lang.py
num2textilka-0.1.2.dist-info/LICENSE
num2textilka-0.1.2.dist-info/METADATA
num2textilka-0.1.2.dist-info/WHEEL
num2textilka-0.1.2.dist-info/top_level.txt
num2textilka-0.1.2.dist-info/RECORD
