Metadata-Version: 2.1
Name: num2textilka
Version: 0.1.2
Summary: Number to Text Convertor
Author-email: "Arash Hamzei, Erfan Ahmadi Moqadam, Mahdi Yaghoubi" <baxizhere@gmail.com>
Classifier: Programming Language :: Python :: 3
Classifier: License :: OSI Approved :: MIT License
Classifier: Operating System :: OS Independent
Requires-Python: >=3.6
License-File: LICENSE
